jps_release_audit_utils/__init__.py
jps_release_audit_utils/commit_report.py
jps_release_audit_utils/config_loader.py
jps_release_audit_utils/constants.py
jps_release_audit_utils/excel_writer.py
jps_release_audit_utils/git_ops.py
jps_release_audit_utils/git_true_changes_report.py
jps_release_audit_utils/help.py
jps_release_audit_utils/repo_helper.py
jps_release_audit_utils/conf/config.yaml
jps_release_audit_utils-0.9.0.dist-info/licenses/LICENSE
jps_release_audit_utils-0.9.0.dist-info/METADATA
jps_release_audit_utils-0.9.0.dist-info/WHEEL
jps_release_audit_utils-0.9.0.dist-info/entry_points.txt
jps_release_audit_utils-0.9.0.dist-info/top_level.txt
jps_release_audit_utils-0.9.0.dist-info/RECORD
